cmsis_svd/__init__.py
cmsis_svd/model.py
cmsis_svd/parser.py
cmsis_svd/py.typed
cmsis_svd/schemas/CMSIS-SVD_1_0.xsd
cmsis_svd/schemas/CMSIS-SVD_1_1.xsd
cmsis_svd/schemas/CMSIS-SVD_1_2.xsd
cmsis_svd/schemas/CMSIS-SVD_1_3_1.xsd
cmsis_svd/schemas/CMSIS-SVD_1_3_10.xsd
cmsis_svd/schemas/CMSIS-SVD_1_3_11.xsd
cmsis_svd/schemas/CMSIS-SVD_1_3_2.xsd
cmsis_svd/schemas/CMSIS-SVD_1_3_3.xsd
cmsis_svd/schemas/CMSIS-SVD_1_3_4.xsd
cmsis_svd/schemas/CMSIS-SVD_1_3_5.xsd
cmsis_svd/schemas/CMSIS-SVD_1_3_6.xsd
cmsis_svd/schemas/CMSIS-SVD_1_3_7.xsd
cmsis_svd/schemas/CMSIS-SVD_1_3_8.xsd
cmsis_svd/schemas/CMSIS-SVD_1_3_9.xsd
cmsis_svd/schemas/metadata.txt
cmsis_svd/serializers/__init__.py
cmsis_svd/serializers/json.py
cmsis_svd/serializers/xml.py
cmsis_svd-0.6.dist-info/METADATA
cmsis_svd-0.6.dist-info/WHEEL
cmsis_svd-0.6.dist-info/top_level.txt
cmsis_svd-0.6.dist-info/RECORD
