Metadata-Version: 2.1
Name: cmsis-svd
Version: 0.6
Summary: CMSIS SVD parser
Home-page: https://github.com/cmsis-svd/cmsis-svd
Author: cmsis-svd Authors
Author-email: 
License: Apache 2.0
Classifier: Development Status :: 4 - Beta
Classifier: License :: OSI Approved :: Apache Software License
Classifier: Programming Language :: Python
Classifier: Topic :: System :: Hardware
Classifier: Topic :: System :: Boot :: Init
Classifier: Topic :: System :: Hardware :: Hardware Drivers
Classifier: Topic :: Software Development :: Code Generators
Classifier: Topic :: Software Development :: Embedded Systems
Classifier: Topic :: System :: Operating System Kernels
Classifier: Topic :: Utilities
Classifier: Topic :: Text Processing :: Markup
Requires-Python: >=3.8
Requires-Dist: six>=1.10
Requires-Dist: lxml
Provides-Extra: dev
Requires-Dist: nose2; extra == "dev"
